khartoum/__init__.py
khartoum/__main__.py
khartoum/gzip_util.py
khartoum/server.py
khartoum/test_server.py
khartoum/upload.py
khartoum-2.1.1.dist-info/LICENSE
khartoum-2.1.1.dist-info/METADATA
khartoum-2.1.1.dist-info/WHEEL
khartoum-2.1.1.dist-info/top_level.txt
khartoum-2.1.1.dist-info/RECORD
